{
  "id": "product_grid",
  "type": "SharedSlice",
  "name": "ProductGrid",
  "description": "ProductGrid",
  "variations": [
    {
      "id": "default-slice",
      "name": "Default slice",
      "docURL": "...",
      "version": "sktwi1xtmkfgx8626",
      "description": "ProductGrid",
      "primary": {
        "title": {
          "type": "StructuredText",
          "config": {
            "single": "heading1",
            "label": "Title",
            "placeholder": "This is where it all begins..."
          }
        },
        "columns": {
          "config": {
            "label": "Columns",
            "placeholder": "Columns on a large screen",
            "options": [
              "2",
              "3"
            ],
            "default_value": "2"
          },
          "type": "Select"
        }
      },
      "items": {
        "image": {
          "config": {
            "label": "Top Image",
            "constraint": {},
            "thumbnails": []
          },
          "type": "Image"
        },
        "hoverImage": {
          "config": {
            "label": "Under Image",
            "constraint": {},
            "thumbnails": []
          },
          "type": "Image"
        },
        "title": {
          "config": {
            "label": "Title",
            "placeholder": ""
          },
          "type": "Text"
        },
        "price": {
          "config": {
            "label": "Price",
            "placeholder": ""
          },
          "type": "Number"
        },
        "fullWidth": {
          "config": {
            "label": "Full Width?",
            "placeholder": "",
            "placeholder_false": "false",
            "placeholder_true": "true",
            "default_value": true
          },
          "type": "Boolean"
        }
      }
    }
  ]
}